MANIFEST.in
README.rst
setup.py
rdcli/RDWorker.py
rdcli/__init__.py
rdcli/config.py
rdcli/rdcli.py
rdcli.egg-info/PKG-INFO
rdcli.egg-info/SOURCES.txt
rdcli.egg-info/dependency_links.txt
rdcli.egg-info/entry_points.txt
rdcli.egg-info/top_level.txt