Metadata-Version: 1.1
Name: rdcli
Version: 0.8.3
Summary: Use Read-Debrid from your command line !
Home-page: https://github.com/MrMitch/realdebrid-CLI
Author: MrMitch
Author-email: contact@mickael-goetz.com
License: MIT
Platform: UNKNOWN
Classifier: Programming Language :: Python
Classifier: Development Status :: 5 - Production/Stable
Classifier: Environment :: Console
Classifier: Natural Language :: English
Classifier: Operating System :: OS Independent
Classifier: Programming Language :: Python :: 2.7
Classifier: Topic :: Internet
